async_tls_client/__init__.py
async_tls_client/cffi.py
async_tls_client/cookies.py
async_tls_client/exceptions.py
async_tls_client/response.py
async_tls_client/types.py
async_tls_client/dependencies/__init__.py
async_tls_client/dependencies/tls-client-32.dll
async_tls_client/dependencies/tls-client-64.dll
async_tls_client/dependencies/tls-client-amd64.so
async_tls_client/dependencies/tls-client-arm64.dylib
async_tls_client/dependencies/tls-client-arm64.so
async_tls_client/dependencies/tls-client-x86.dylib
async_tls_client/dependencies/tls-client-x86.so
async_tls_client/session/__init__.py
async_tls_client/session/request_payload_builder.py
async_tls_client/session/session.py
async_tls_client-2.0.4.dist-info/licenses/LICENSE
async_tls_client-2.0.4.dist-info/METADATA
async_tls_client-2.0.4.dist-info/WHEEL
async_tls_client-2.0.4.dist-info/top_level.txt
async_tls_client-2.0.4.dist-info/RECORD
