Metadata-Version: 2.4
Name: async_tls_client
Version: 2.0.4
Summary: Asyncio TLS client with advanced fingerprinting capabilities
Author: Diprog, Florian Zager
License: MIT License
Project-URL: Homepage, https://github.com/diprog/python-tls-client-async
Project-URL: Documentation, https://github.com/diprog/python-tls-client-async#readme
Project-URL: Original, https://github.com/FlorianREGAZ/Python-Tls-Client
Project-URL: Issues, https://github.com/diprog/python-tls-client-async/issues
Project-URL: Changelog, https://github.com/diprog/python-tls-client-async/releases
Keywords: tls,asyncio,http-client,ja3,fingerprinting,http2
Classifier: Environment :: Web Environment
Classifier: Intended Audience :: Developers
Classifier: License :: OSI Approved :: MIT License
Classifier: Natural Language :: English
Classifier: Operating System :: OS Independent
Classifier: Programming Language :: Python :: 3
Classifier: Programming Language :: Python :: 3.9
Classifier: Programming Language :: Python :: 3.10
Classifier: Programming Language :: Python :: 3.11
Classifier: Programming Language :: Python :: 3.12
Classifier: Programming Language :: Python :: 3.13
Classifier: Topic :: Internet :: WWW/HTTP
Classifier: Topic :: Software Development :: Libraries
Requires-Python: >=3.9
License-File: LICENSE
Requires-Dist: nocasedict
Requires-Dist: typing-extensions
Provides-Extra: test
Requires-Dist: pytest>=7.0; extra == "test"
Requires-Dist: pytest-asyncio>=0.20; extra == "test"
Dynamic: license-file
